just_distribute/__init__.py
just_distribute/decorator.py
just_distribute-0.1.6.dist-info/METADATA
just_distribute-0.1.6.dist-info/WHEEL
just_distribute-0.1.6.dist-info/RECORD
