Metadata-Version: 2.4
Name: just-distribute
Version: 0.1.6
Summary: Provides a @distribute decorator that enables concurrent execution of functions without boilerplate code.
Project-URL: Repository, https://github.com/jakubgajski/just_distribute
Author-email: Jakub Gajski <jakub.gajski@gmail.com>
License-Expression: MIT
Keywords: concurrency,concurrent,decorator,distributed,parallel,parallelism
Requires-Python: >=3.10
Requires-Dist: pathos<0.4,>=0.3.2
Requires-Dist: protobuf>=6.31.1
Requires-Dist: psutil<6,>=5.9.8
Requires-Dist: ray[client]<3,>=2.43.0
Requires-Dist: requests>=2.32.4
